{
  "version": "1.3.5",
  "description": "A cross-platform keyboard-driven minimal launcher (like Alfred/Raycast)",
  "homepage": "https://github.com/yukimemi/shun",
  "license": "MIT",
  "architecture": {
    "64bit": {
      "url": "https://github.com/yukimemi/shun/releases/download/v1.3.5/shun-windows-x64.zip",
      "hash": "cc4b7166a009b7066ad4238f8146d12b550bc15ffbdf7597016ef6b4cffa54ca"
    }
  },
  "bin": "shun.exe",
  "shortcuts": [
    [
      "shun.exe",
      "shun"
    ]
  ],
  "checkver": {
    "github": "https://github.com/yukimemi/shun"
  },
  "autoupdate": {
    "architecture": {
      "64bit": {
        "url": "https://github.com/yukimemi/shun/releases/download/v$version/shun-windows-x64.zip",
        "hash": {
          "url": "https://github.com/yukimemi/shun/releases/download/v$version/shun-windows-x64.zip.sha256"
        }
      }
    }
  }
}
