{
  "version": "3.5.3",
  "description": "A cross-platform keyboard-driven minimal launcher (like Alfred/Raycast)",
  "homepage": "https://github.com/yukimemi/shun",
  "license": "MIT",
  "architecture": {
    "64bit": {
      "url": "https://github.com/yukimemi/shun/releases/download/v3.5.3/shun-windows-x64.zip",
      "hash": "afa10db7d27ac1b09f3100f1c99c0bdabcdb9cf5a88b09abf84c9e042ea1bb5d"
    }
  },
  "bin": "shun.exe",
  "shortcuts": [
    [
      "shun.exe",
      "shun"
    ]
  ],
  "checkver": {
    "github": "https://github.com/yukimemi/shun"
  },
  "autoupdate": {
    "architecture": {
      "64bit": {
        "url": "https://github.com/yukimemi/shun/releases/download/v$version/shun-windows-x64.zip",
        "hash": {
          "url": "https://github.com/yukimemi/shun/releases/download/v$version/shun-windows-x64.zip.sha256"
        }
      }
    }
  }
}
